spacelabel/__init__.py
spacelabel/__main__.py
spacelabel/models/__init__.py
spacelabel/models/feature.py
spacelabel/models/dataset/__init__.py
spacelabel/models/dataset/cdf.py
spacelabel/models/dataset/hdf5.py
spacelabel/models/dataset/load.py
spacelabel/models/dataset/preprocessed.py
spacelabel/presenters/__init__.py
spacelabel/views/__init__.py
spacelabel/views/matplotlib.py
SPACE_labelling_tool-2.0.dist-info/LICENSE
SPACE_labelling_tool-2.0.dist-info/METADATA
SPACE_labelling_tool-2.0.dist-info/WHEEL
SPACE_labelling_tool-2.0.dist-info/entry_points.txt
SPACE_labelling_tool-2.0.dist-info/top_level.txt
SPACE_labelling_tool-2.0.dist-info/RECORD
