Metadata-Version: 2.1
Name: SPACE-labelling-tool
Version: 2.0
Summary: Interactive python tool designed to label radio emission features of interest in a temporal-spectral map
Home-page: https://github.com/CorentinLouis/SPACE_labelling_tool
Author: Corentin K. Louis, C. M. Jackman, S. W. Mangham, K. D. Smith, E. P. O'Dwyer, A. Empey, B. Cecconi, A. Boudouma, P. Zarka, S. Maloney
Maintainer: Corentin Louis
Maintainer-email: corentin.louis@dias.ie
License: MIT
Platform: UNKNOWN
Classifier: Programming Language :: Python :: 3
Classifier: License :: OSI Approved :: MIT License
Classifier: Operating System :: POSIX
Requires-Dist: wheel
Requires-Dist: scipy
Requires-Dist: numpy
Requires-Dist: matplotlib
Requires-Dist: shapely
Requires-Dist: astropy
Requires-Dist: h5py
Requires-Dist: TFCat
